alu.v
//ALU encoding
//4'b0000 ADD
//4'b0001 SUB
//4'b0010 AND
//4'b0011 OR
//4'b0100 XOR
//4;b0101 SLL
//4'b0110 SRL
//4'b0111 SRA
//4'b1000 SLT
//4'b1001 SLTU
//4'b1010 LUI

module alu (
    input [31:0] a,
    input [31:0] b,
    input [3:0] alu_ctrl,
    output reg [31:0] result,
    output wire zero,
    output wire negative,
    output wire overflow
);

//shift amount
wire [4:0] shift_bit = b[4:0];

//combinational logic
always @(*) begin
    case(alu_ctrl)
        4'b0000: result = a + b;
        4'b0001: result = a - b;
        4'b0010: result = a & b;
        4'b0011: result = a | b;
        4'b0100: result = a ^ b;
        4'b0101: result = a << shift_bit;
        4'b0110: result = a >> shift_bit;
        4'b0111: result = $signed(a) >>> shift_bit;
        4'b1000: result = {31'b0, ($signed(a) < $signed(b))};
        4'b1001: result = {31'b0, (a < b)};
        4'b1010: result = b;
        default: result = 32'b0;
    endcase
end

//status flags
assign zero = (result == 32'b0);
assign negative = result[31];

wire add_overflow = (alu_ctrl == 4'b0000) && ((a[31] & b[31] & ~result[31]) | (~a[31] & ~b[31] & result[31]));
wire sub_overflow = (alu_ctrl == 4'b0001) && ((~a[31] & b[31] & result[31]) | (a[31] & ~b[31] & ~result[31]));

assign overflow = add_overflow | sub_overflow;

endmodule

alu_tb.v
// ============================================================
//  ALU testbench
//  Run with:  iverilog -o alu_tb alu_tb.v alu.v && vvp alu_tb
// ============================================================

`timescale 1ns/1ps

module alu_tb;

    reg  [31:0] a, b;
    reg  [ 3:0] alu_ctrl;
    wire [31:0] result;
    wire        zero, negative, overflow;

    integer pass = 0;
    integer fail = 0;

    // instantiate DUT
    alu dut (
        .a        (a),
        .b        (b),
        .alu_ctrl (alu_ctrl),
        .result   (result),
        .zero     (zero),
        .negative (negative),
        .overflow (overflow)
    );

    // ---- task: check one result --------------------------------
    task check;
        input [31:0] expected;
        input [63:0] label;   // 8-char ASCII tag
        begin
            #1;
            if (result === expected) begin
                $display("PASS  %-8s  a=%08h b=%08h ctrl=%b => %08h",
                         label, a, b, alu_ctrl, result);
                pass = pass + 1;
            end else begin
                $display("FAIL  %-8s  a=%08h b=%08h ctrl=%b => got %08h expected %08h",
                         label, a, b, alu_ctrl, result, expected);
                fail = fail + 1;
            end
        end
    endtask

    initial begin


        $dumpfile("alu.vcd");
        $dumpvars(0, alu_tb);

        // ---- ADD -----------------------------------------------
        alu_ctrl = 4'b0000;
        a = 32'd10;   b = 32'd20;   check(32'd30,           "ADD     ");
        a = 32'hFFFFFFFF; b = 32'd1; check(32'd0,           "ADD_WRAP");

        // ---- SUB -----------------------------------------------
        alu_ctrl = 4'b0001;
        a = 32'd30;   b = 32'd10;   check(32'd20,           "SUB     ");
        a = 32'd0;    b = 32'd1;    check(32'hFFFFFFFF,     "SUB_WRAP");

        // ---- AND -----------------------------------------------
        alu_ctrl = 4'b0010;
        a = 32'hFF00FF00; b = 32'h0F0F0F0F; check(32'h0F000F00, "AND     ");

        // ---- OR ------------------------------------------------
        alu_ctrl = 4'b0011;
        a = 32'hF0F0F0F0; b = 32'h0F0F0F0F; check(32'hFFFFFFFF, "OR      ");

        // ---- XOR -----------------------------------------------
        alu_ctrl = 4'b0100;
        a = 32'hAAAAAAAA; b = 32'h55555555; check(32'hFFFFFFFF, "XOR     ");
        a = 32'hDEADBEEF; b = 32'hDEADBEEF; check(32'h00000000, "XOR_SAME");

        // ---- SLL -----------------------------------------------
        alu_ctrl = 4'b0101;
        a = 32'h00000001; b = 32'd4;  check(32'h00000010,   "SLL     ");
        a = 32'h00000001; b = 32'd31; check(32'h80000000,   "SLL_31  ");

        // ---- SRL -----------------------------------------------
        alu_ctrl = 4'b0110;
        a = 32'h80000000; b = 32'd1;  check(32'h40000000,   "SRL     ");
        a = 32'hFFFFFFFF; b = 32'd4;  check(32'h0FFFFFFF,   "SRL_4   ");

        // ---- SRA -----------------------------------------------
        alu_ctrl = 4'b0111;
        a = 32'h80000000; b = 32'd1;  check(32'hC0000000,   "SRA     ");
        a = 32'hFFFFFFFF; b = 32'd4;  check(32'hFFFFFFFF,   "SRA_NEG ");

        // ---- SLT (signed) --------------------------------------
        alu_ctrl = 4'b1000;
        a = 32'hFFFFFFFF; b = 32'd1;  check(32'd1,          "SLT_NEG ");  // -1 < 1
        a = 32'd1;        b = 32'd1;  check(32'd0,          "SLT_EQ  ");
        a = 32'd2;        b = 32'd1;  check(32'd0,          "SLT_GT  ");

        // ---- SLTU (unsigned) -----------------------------------
        alu_ctrl = 4'b1001;
        a = 32'hFFFFFFFF; b = 32'd1;  check(32'd0,          "SLTU_BIG");  // big > 1
        a = 32'd0;        b = 32'd1;  check(32'd1,          "SLTU_LT ");

        // ---- LUI pass-through ----------------------------------
        alu_ctrl = 4'b1010;
        a = 32'hDEADBEEF; b = 32'h12345000; check(32'h12345000, "LUI     ");

        // ---- zero flag -----------------------------------------
        alu_ctrl = 4'b0001;
        a = 32'd42; b = 32'd42;
        #1;
        if (zero !== 1'b1) begin
            $display("FAIL  ZERO_FLG expected zero=1 got zero=%b", zero);
            fail = fail + 1;
        end else begin
            $display("PASS  ZERO_FLG");
            pass = pass + 1;
        end

        // ---- negative flag -------------------------------------
        alu_ctrl = 4'b0000;
        a = 32'h80000000; b = 32'd0;
        #1;
        if (negative !== 1'b1) begin
            $display("FAIL  NEG_FLG  expected negative=1 got negative=%b", negative);
            fail = fail + 1;
        end else begin
            $display("PASS  NEG_FLG");
            pass = pass + 1;
        end

        // ---- overflow flag -------------------------------------
        alu_ctrl = 4'b0000;   // ADD: max_positive + 1 => overflow
        a = 32'h7FFFFFFF; b = 32'd1;
        #1;
        if (overflow !== 1'b1) begin
            $display("FAIL  OVF_FLG  expected overflow=1 got overflow=%b", overflow);
            fail = fail + 1;
        end else begin
            $display("PASS  OVF_FLG");
            pass = pass + 1;
        end

        // ---- summary -------------------------------------------
        $display("\n========================================");
        $display("  %0d passed   %0d failed", pass, fail);
        $display("========================================");
        $finish;
    end

endmodule

alu.vcd
$date
	Sun Jun 28 15:14:12 2026
$end
$version
	Icarus Verilog
$end
$timescale
	1ps
$end
$scope module alu_tb $end
$var wire 1 ! zero $end
$var wire 32 " result [31:0] $end
$var wire 1 # overflow $end
$var wire 1 $ negative $end
$var reg 32 % a [31:0] $end
$var reg 4 & alu_ctrl [3:0] $end
$var reg 32 ' b [31:0] $end
$var integer 32 ( fail [31:0] $end
$var integer 32 ) pass [31:0] $end
$scope module dut $end
$var wire 32 * a [31:0] $end
$var wire 1 + add_overflow $end
$var wire 4 , alu_ctrl [3:0] $end
$var wire 32 - b [31:0] $end
$var wire 1 # overflow $end
$var wire 1 . sub_overflow $end
$var wire 1 ! zero $end
$var wire 5 / shift_bit [4:0] $end
$var wire 1 $ negative $end
$var reg 32 0 result [31:0] $end
$upscope $end
$scope task check $end
$var reg 32 1 expected [31:0] $end
$var reg 64 2 label [63:0] $end
$upscope $end
$upscope $end
$enddefinitions $end
$comment Show the parameter values. $end
$dumpall
$end
#0
$dumpvars
b100000101000100010001000010000000100000001000000010000000100000 2
b11110 1
b11110 0
b10100 /
0.
b10100 -
b0 ,
0+
b1010 *
b0 )
b0 (
b10100 '
b0 &
b1010 %
0$
0#
b11110 "
0!
$end
#1000
b1 /
1!
b0 "
b0 0
b100000101000100010001000101111101010111010100100100000101010000 2
b0 1
b1 '
b1 -
b11111111111111111111111111111111 %
b11111111111111111111111111111111 *
b1 )
#2000
0#
b1010 /
0!
b10100 "
b10100 0
0.
b101001101010101010000100010000000100000001000000010000000100000 2
b10100 1
b1010 '
b1010 -
b11110 %
b11110 *
b1 &
b1 ,
b10 )
#3000
1$
b1 /
b11111111111111111111111111111111 "
b11111111111111111111111111111111 0
b101001101010101010000100101111101010111010100100100000101010000 2
b11111111111111111111111111111111 1
b1 '
b1 -
b0 %
b0 *
b11 )
#4000
0$
b1111 /
b1111000000000000111100000000 "
b1111000000000000111100000000 0
b100000101001110010001000010000000100000001000000010000000100000 2
b1111000000000000111100000000 1
b1111000011110000111100001111 '
b1111000011110000111100001111 -
b11111111000000001111111100000000 %
b11111111000000001111111100000000 *
b10 &
b10 ,
b100 )
#5000
1$
b11111111111111111111111111111111 "
b11111111111111111111111111111111 0
b100111101010010001000000010000000100000001000000010000000100000 2
b11111111111111111111111111111111 1
b11110000111100001111000011110000 %
b11110000111100001111000011110000 *
b11 &
b11 ,
b101 )
#6000
b10101 /
b101100001001111010100100010000000100000001000000010000000100000 2
b1010101010101010101010101010101 '
b1010101010101010101010101010101 -
b10101010101010101010101010101010 %
b10101010101010101010101010101010 *
b100 &
b100 ,
b110 )
#7000
0$
b1111 /
1!
b0 "
b0 0
b101100001001111010100100101111101010011010000010100110101000101 2
b0 1
b11011110101011011011111011101111 '
b11011110101011011011111011101111 -
b11011110101011011011111011101111 %
b11011110101011011011111011101111 *
b111 )
#8000
b100 /
0!
b10000 "
b10000 0
b101001101001100010011000010000000100000001000000010000000100000 2
b10000 1
b100 '
b100 -
b1 %
b1 *
b101 &
b101 ,
b1000 )
#9000
1$
b10000000000000000000000000000000 "
b10000000000000000000000000000000 0
b11111 /
b101001101001100010011000101111100110011001100010010000000100000 2
b10000000000000000000000000000000 1
b11111 '
b11111 -
b1001 )
#10000
0$
b1 /
b1000000000000000000000000000000 "
b1000000000000000000000000000000 0
b101001101010010010011000010000000100000001000000010000000100000 2
b1000000000000000000000000000000 1
b1 '
b1 -
b10000000000000000000000000000000 %
b10000000000000000000000000000000 *
b110 &
b110 ,
b1010 )
#11000
b100 /
b1111111111111111111111111111 "
b1111111111111111111111111111 0
b101001101010010010011000101111100110100001000000010000000100000 2
b1111111111111111111111111111 1
b100 '
b100 -
b11111111111111111111111111111111 %
b11111111111111111111111111111111 *
b1011 )
#12000
1$
b1 /
b11000000000000000000000000000000 "
b11000000000000000000000000000000 0
b101001101010010010000010010000000100000001000000010000000100000 2
b11000000000000000000000000000000 1
b1 '
b1 -
b10000000000000000000000000000000 %
b10000000000000000000000000000000 *
b111 &
b111 ,
b1100 )
#13000
b100 /
b11111111111111111111111111111111 "
b11111111111111111111111111111111 0
b101001101010010010000010101111101001110010001010100011100100000 2
b11111111111111111111111111111111 1
b100 '
b100 -
b11111111111111111111111111111111 %
b11111111111111111111111111111111 *
b1101 )
#14000
0$
b1 /
b1 "
b1 0
b101001101001100010101000101111101001110010001010100011100100000 2
b1 1
b1 '
b1 -
b1000 &
b1000 ,
b1110 )
#15000
1!
b0 "
b0 0
b101001101001100010101000101111101000101010100010010000000100000 2
b0 1
b1 %
b1 *
b1111 )
#16000
b101001101001100010101000101111101000111010101000010000000100000 2
b10 %
b10 *
b10000 )
#17000
b101001101001100010101000101010101011111010000100100100101000111 2
b11111111111111111111111111111111 %
b11111111111111111111111111111111 *
b1001 &
b1001 ,
b10001 )
#18000
0!
b1 "
b1 0
b101001101001100010101000101010101011111010011000101010000100000 2
b1 1
b0 %
b0 *
b10010 )
#19000
b0 /
b10010001101000101000000000000 "
b10010001101000101000000000000 0
b100110001010101010010010010000000100000001000000010000000100000 2
b10010001101000101000000000000 1
b10010001101000101000000000000 '
b10010001101000101000000000000 -
b11011110101011011011111011101111 %
b11011110101011011011111011101111 *
b1010 &
b1010 ,
b10011 )
#20000
0#
b1010 /
1!
b0 "
b0 0
0.
b101010 '
b101010 -
b101010 %
b101010 *
b1 &
b1 ,
b10100 )
#21000
0#
0+
1$
b0 /
0!
b10000000000000000000000000000000 "
b10000000000000000000000000000000 0
b0 '
b0 -
b10000000000000000000000000000000 %
b10000000000000000000000000000000 *
b0 &
b0 ,
b10101 )
#22000
1#
1+
b1 /
b1 '
b1 -
b1111111111111111111111111111111 %
b1111111111111111111111111111111 *
b10110 )
#23000
b10111 )
